thothai_data_cli/__init__.py
thothai_data_cli/cli.py
thothai_data_cli/config.py
thothai_data_cli/docs/DATA_CLI_USER_MANUAL_IT.md
thothai_data_cli-1.0.2.dist-info/METADATA
thothai_data_cli-1.0.2.dist-info/WHEEL
thothai_data_cli-1.0.2.dist-info/entry_points.txt
thothai_data_cli-1.0.2.dist-info/licenses/LICENSE.md
thothai_data_cli-1.0.2.dist-info/RECORD
