Metadata-Version: 2.4
Name: thothai-data-cli
Version: 1.0.2
Summary: CLI for ThothAI data exchange - CSV and SQLite database management
Project-URL: Homepage, https://github.com/mptyl/ThothAI
Project-URL: Repository, https://github.com/mptyl/ThothAI
Author: Marco Pancotti
License: 
License-File: LICENSE.md
Keywords: cli,csv,data-exchange,docker,sqlite,thothai
Classifier: Development Status :: 4 - Beta
Classifier: Environment :: Console
Classifier: Intended Audience :: Developers
Classifier: License :: OSI Approved :: Apache Software License
Classifier: Operating System :: OS Independent
Classifier: Programming Language :: Python :: 3
Classifier: Programming Language :: Python :: 3.9
Classifier: Programming Language :: Python :: 3.10
Classifier: Programming Language :: Python :: 3.11
Classifier: Programming Language :: Python :: 3.12
Classifier: Programming Language :: Python :: 3.13
Classifier: Topic :: Database
Classifier: Topic :: Utilities
Requires-Python: >=3.9
Requires-Dist: click>=8.0
Requires-Dist: pyyaml>=6.0
Requires-Dist: rich>=13.0
Requires-Dist: thothai-cli-core
